soga_tts/__init__.py
soga_tts/cli.py
soga_tts/fixed_duration_tts.py
soga_tts/my_tts.py
soga_tts-0.1.5.dist-info/METADATA
soga_tts-0.1.5.dist-info/WHEEL
soga_tts-0.1.5.dist-info/entry_points.txt
soga_tts-0.1.5.dist-info/top_level.txt
soga_tts-0.1.5.dist-info/RECORD
