Metadata-Version: 2.4
Name: soga-tts
Version: 0.1.5
Summary: fix duration TTS tool - combines intelligent TTS with LLM
Author-email: Your Name <your.email@example.com>
Classifier: Programming Language :: Python :: 3
Classifier: Operating System :: OS Independent
Requires-Python: >=3.10
Requires-Dist: edge-tts>=7.0.2
Requires-Dist: moviepy>=2.2.1
Requires-Dist: openai>=1.97.0
Provides-Extra: test
Requires-Dist: pytest>=7.0; extra == "test"
Requires-Dist: pytest-asyncio>=0.21.0; extra == "test"
Requires-Dist: pytest-mock>=3.10.0; extra == "test"
Requires-Dist: pytest-cov>=4.0.0; extra == "test"
